microforge/__init__.py
microforge/__main__.py
microforge/cli.py
microforge/config.py
microforge/generator.py
microforge/py.typed
microforge/templates/.dockerignore.j2
microforge/templates/app/__init__.py.j2
microforge/templates/app/auth/__init__.py.j2
microforge/templates/app/auth/oauth2.py.j2
microforge/templates/app/core/__init__.py.j2
microforge/templates/app/core/config.py.j2
microforge/templates/app/core/logging.py.j2
microforge/templates/app/core/telemetry.py.j2
microforge/templates/app/db/__init__.py.j2
microforge/templates/app/db/database.py.j2
microforge/templates/app/db/models.py.j2
microforge/templates/app/main.py.j2
microforge/templates/app/routes/__init__.py.j2
microforge/templates/app/routes/health.py.j2
microforge/templates/ci/azure-pipelines.yml.j2
microforge/templates/ci/github-workflows.yml.j2
microforge/templates/ci/gitlab-ci.yml.j2
microforge/templates/docker-compose.yml.j2
microforge/templates/Dockerfile.j2
microforge/templates/gitignore.j2
microforge/templates/helm/Chart.yaml.j2
microforge/templates/helm/templates/deployment.yaml.j2
microforge/templates/helm/templates/service.yaml.j2
microforge/templates/helm/values.yaml.j2
microforge/templates/pyproject.toml.j2
microforge/templates/README.md.j2
microforge/templates/tests/__init__.py.j2
microforge/templates/tests/conftest.py.j2
microforge/templates/tests/test_health.py.j2
microforge/templates/worker/__init__.py.j2
microforge/templates/worker/worker.py.j2
microforge_cli-0.1.1.dist-info/entry_points.txt
microforge_cli-0.1.1.dist-info/METADATA
microforge_cli-0.1.1.dist-info/WHEEL
microforge_cli-0.1.1.dist-info/RECORD
