Metadata-Version: 2.4
Name: microforge-cli
Version: 0.1.1
Summary: A production-ready project generator for modern Python microservices
License: MIT
Keywords: microservices,fastapi,celery,cli,generator,scaffold
Author: Klejdi
Author-email: klejdi94@gmail.com
Requires-Python: >=3.9,<4.0
Classifier: Development Status :: 4 - Beta
Classifier: Intended Audience :: Developers
Classifier: License :: OSI Approved :: MIT License
Classifier: Programming Language :: Python :: 3
Classifier: Programming Language :: Python :: 3.9
Classifier: Programming Language :: Python :: 3.10
Classifier: Programming Language :: Python :: 3.11
Classifier: Programming Language :: Python :: 3.12
Classifier: Programming Language :: Python :: 3.13
Classifier: Programming Language :: Python :: 3.14
Requires-Dist: jinja2 (>=3.1.0,<4.0.0)
Requires-Dist: pyyaml (>=6.0.1,<7.0.0)
Project-URL: Homepage, https://github.com/klejdi94/microforge-cli
Project-URL: Repository, https://github.com/klejdi94/microforge-cli
